[
   {
      "id": "62895379169488@s.whatsapp.net",
      "balance": 100000000000000110
   },
   {
      "id": "79773878825@s.whatsapp.net",
      "balance": 88888888888888900
   },
   {
      "id": "6285751337466@s.whatsapp.net",
      "balance": 229
   },
   {
      "id": "6281326571751@s.whatsapp.net",
      "balance": 590
   },
   {
      "id": "628565337357@s.whatsapp.net",
      "balance": 1484
   },
   {
      "id": "6285218115220@s.whatsapp.net",
      "balance": 189
   },
   {
      "id": "628811759935@s.whatsapp.net",
      "balance": 35
   },
   {
      "id": "6287771766903@s.whatsapp.net",
      "balance": 97
   },
   {
      "id": "6285712734432@s.whatsapp.net",
      "balance": 326
   },
   {
      "id": "6285793773780@s.whatsapp.net",
      "balance": 11
   },
   {
      "id": "6288223835987@s.whatsapp.net",
      "balance": 34
   },
   {
      "id": "6285816199217@s.whatsapp.net",
      "balance": 14
   },
   {
      "id": "6285388584943@s.whatsapp.net",
      "balance": 17
   },
   {
      "id": "6282128736729@s.whatsapp.net",
      "balance": 107
   },
   {
      "id": "62895375843900@s.whatsapp.net",
      "balance": 110
   },
   {
      "id": "6283875527734@s.whatsapp.net",
      "balance": 727
   },
   {
      "id": "628987245868@s.whatsapp.net",
      "balance": 21
   },
   {
      "id": "6283813443300@s.whatsapp.net",
      "balance": 28
   },
   {
      "id": "6281515388765@s.whatsapp.net",
      "balance": 7
   },
   {
      "id": "6285792304047@s.whatsapp.net",
      "balance": 27
   },
   {
      "id": "6282215017438@s.whatsapp.net",
      "balance": 18
   },
   {
      "id": "6285815975368@s.whatsapp.net",
      "balance": 108
   },
   {
      "id": "62882003820508@s.whatsapp.net",
      "balance": 111
   },
   {
      "id": "6288296647770@s.whatsapp.net",
      "balance": 9
   },
   {
      "id": "6283107412473@s.whatsapp.net",
      "balance": 38
   },
   {
      "id": "6281393791682@s.whatsapp.net",
      "balance": 18
   },
   {
      "id": "6283829704784@s.whatsapp.net",
      "balance": 402
   },
   {
      "id": "6281360466178@s.whatsapp.net",
      "balance": 10
   },
   {
      "id": "628176660047@s.whatsapp.net",
      "balance": 245
   },
   {
      "id": "6282189975711@s.whatsapp.net",
      "balance": 17
   },
   {
      "id": "6281331404857@s.whatsapp.net",
      "balance": 57
   },
   {
      "id": "6288247157565@s.whatsapp.net",
      "balance": 57
   },
   {
      "id": "62895384163191@s.whatsapp.net",
      "balance": 42
   },
   {
      "id": "6281996110334@s.whatsapp.net",
      "balance": 12
   },
   {
      "id": "6281548935877@s.whatsapp.net",
      "balance": 94
   },
   {
      "id": "6282244557523@s.whatsapp.net",
      "balance": 26
   },
   {
      "id": "6285242807614@s.whatsapp.net",
      "balance": 23
   },
   {
      "id": "6281215350385@s.whatsapp.net",
      "balance": 94
   },
   {
      "id": "6281311776826@s.whatsapp.net",
      "balance": 22
   },
   {
      "id": "6283120847903@s.whatsapp.net",
      "balance": 67
   },
   {
      "id": "62881027232255@s.whatsapp.net",
      "balance": 12
   },
   {
      "id": "6288235653810@s.whatsapp.net",
      "balance": 281
   },
   {
      "id": "6281359833156@s.whatsapp.net",
      "balance": 21
   },
   {
      "id": "6285780582149@s.whatsapp.net",
      "balance": 12
   },
   {
      "id": "6288279973678@s.whatsapp.net",
      "balance": 5
   },
   {
      "id": "6285798471608@s.whatsapp.net",
      "balance": 34
   },
   {
      "id": "6285770795197@s.whatsapp.net",
      "balance": 1
   },
   {
      "id": "6285861811241@s.whatsapp.net",
      "balance": 10
   },
   {
      "id": "6288211506750@s.whatsapp.net",
      "balance": 4
   },
   {
      "id": "62877047975400@s.whatsapp.net",
      "balance": 24
   },
   {
      "id": "62882313052889@s.whatsapp.net",
      "balance": 12
   },
   {
      "id": "62857176932312@s.whatsapp.net",
      "balance": 4
   },
   {
      "id": "62895630415329@s.whatsapp.net",
      "balance": 13
   },
   {
      "id": "628885626434@s.whatsapp.net",
      "balance": 26
   },
   {
      "id": "6281211129249@s.whatsapp.net",
      "balance": 8
   },
   {
      "id": "6282136821559@s.whatsapp.net",
      "balance": 7
   }
]